setup.py
excel_tools/__init__.py
excel_tools/utils.py
excel_tools.egg-info/PKG-INFO
excel_tools.egg-info/SOURCES.txt
excel_tools.egg-info/dependency_links.txt
excel_tools.egg-info/requires.txt
excel_tools.egg-info/top_level.txt
excel_tools/read/__init__.py
excel_tools/read/_xls.py
excel_tools/read/_xlsx.py
excel_tools/read/base_reader.py
excel_tools/write/__init__.py
excel_tools/write/_xlsx.py