Metadata-Version: 2.1
Name: excel-tools
Version: 1.0.15
Summary: This is a tool for excel
Home-page: https://github.com/hakaboom/excel_tools
Author: hakaboom
Author-email: 1534225986@qq.com
License: Apache License 2.0
Platform: UNKNOWN
